spec2nexus/__init__.py
spec2nexus/charts.py
spec2nexus/control_lines.py
spec2nexus/diffractometer-geometries.dict
spec2nexus/diffractometers.py
spec2nexus/extractSpecScan.py
spec2nexus/eznx.py
spec2nexus/eznx_example.py
spec2nexus/nexus.py
spec2nexus/plugin_core.py
spec2nexus/scanf.py
spec2nexus/singletons.py
spec2nexus/spec.py
spec2nexus/specplot.py
spec2nexus/specplot_gallery.py
spec2nexus/utils.py
spec2nexus/writer.py
spec2nexus/data/02_03_setup.dat
spec2nexus/data/03_06_JanTest.dat
spec2nexus/data/05_02_test.dat
spec2nexus/data/20220311-161530.dat
spec2nexus/data/33bm_spec.dat
spec2nexus/data/33id_spec.dat
spec2nexus/data/APS_spec_data.dat
spec2nexus/data/CdOsO
spec2nexus/data/CdSe
spec2nexus/data/Data_Q.h5
spec2nexus/data/README.txt
spec2nexus/data/YSZ011_ALDITO_Fe2O3_planar_fired_1.spc
spec2nexus/data/compression.h5
spec2nexus/data/lmn40.spe
spec2nexus/data/mca_spectra_example.dat
spec2nexus/data/spec_from_spock.spc
spec2nexus/data/startup_1.spec
spec2nexus/data/twoc.dat
spec2nexus/data/usaxs-bluesky-specwritercallback.dat
spec2nexus/data/user6idd.dat
spec2nexus/data/writer_1_3.h5
spec2nexus/data/xpcs_plugin_sample.spec
spec2nexus/data/02_03_setup_fly/README.md
spec2nexus/data/02_03_setup_fly/S10_Blank.h5
spec2nexus/data/02_03_setup_fly/S11_GlassyCarbon_Bob.h5
spec2nexus/data/02_03_setup_fly/S16_GlassyCarbon_M4.h5
spec2nexus/plugins/README.md
spec2nexus/plugins/XPCS.py
spec2nexus/plugins/__init__.py
spec2nexus/plugins/apstools_specwriter.py
spec2nexus/plugins/fallback.py
spec2nexus/plugins/spec_common.py
spec2nexus/plugins/uim.py
spec2nexus/plugins/unicat.py
spec2nexus/plugins/uxml.py
spec2nexus/plugins/uxml.xsd
spec2nexus-2021.2.8.dist-info/licenses/LICENSE
spec2nexus-2021.2.8.dist-info/METADATA
spec2nexus-2021.2.8.dist-info/WHEEL
spec2nexus-2021.2.8.dist-info/entry_points.txt
spec2nexus-2021.2.8.dist-info/top_level.txt
spec2nexus-2021.2.8.dist-info/RECORD
