Metadata-Version: 2.4
Name: spec2nexus
Version: 2021.2.8
Summary: Reads SPEC data files, writes into NeXus HDF5 files.
Author-email: Pete Jemian <prjemian+spec2nexus@gmail.com>
Maintainer-email: Pete Jemian <prjemian+spec2nexus@gmail.com>
License-Expression: CC-BY-4.0
Project-URL: homepage, https://prjemian.github.io/spec2nexus
Project-URL: issues, https://github.com/prjemian/spec2nexus/issues
Project-URL: source, https://github.com/prjemian/spec2nexus
Keywords: SPEC,diffraction,data acquisition,NeXus,HDF5,MatPlotLib
Classifier: Development Status :: 6 - Mature
Classifier: Environment :: Console
Classifier: Environment :: OpenStack
Classifier: Intended Audience :: Science/Research
Classifier: Operating System :: OS Independent
Classifier: Programming Language :: Python
Classifier: Programming Language :: Python :: 3
Classifier: Topic :: Scientific/Engineering
Classifier: Topic :: Scientific/Engineering :: Astronomy
Classifier: Topic :: Scientific/Engineering :: Bio-Informatics
Classifier: Topic :: Scientific/Engineering :: Chemistry
Classifier: Topic :: Scientific/Engineering :: Information Analysis
Classifier: Topic :: Scientific/Engineering :: Interface Engine/Protocol Translator
Classifier: Topic :: Scientific/Engineering :: Mathematics
Classifier: Topic :: Scientific/Engineering :: Physics
Classifier: Topic :: Scientific/Engineering :: Visualization
Classifier: Topic :: Software Development
Classifier: Topic :: Utilities
Requires-Python: >=3.9
License-File: LICENSE
Requires-Dist: h5py
Requires-Dist: lxml
Requires-Dist: matplotlib
Requires-Dist: numpy>=2
Provides-Extra: dev
Requires-Dist: build; extra == "dev"
Requires-Dist: coverage; extra == "dev"
Requires-Dist: coveralls; extra == "dev"
Requires-Dist: isort; extra == "dev"
Requires-Dist: mypy; extra == "dev"
Requires-Dist: pre-commit; extra == "dev"
Requires-Dist: pytest-cov; extra == "dev"
Requires-Dist: pytest; extra == "dev"
Requires-Dist: pytest; extra == "dev"
Requires-Dist: ruff; extra == "dev"
Requires-Dist: setuptools-scm; extra == "dev"
Requires-Dist: twine==6.0.1; extra == "dev"
Provides-Extra: doc
Requires-Dist: markupsafe; extra == "doc"
Requires-Dist: myst-nb; extra == "doc"
Requires-Dist: myst-parser; extra == "doc"
Requires-Dist: nbsphinx; extra == "doc"
Requires-Dist: ophyd; extra == "doc"
Requires-Dist: pydata-sphinx-theme; extra == "doc"
Requires-Dist: setuptools>=77; extra == "doc"
Requires-Dist: setuptools-scm>=8; extra == "doc"
Requires-Dist: setuptools-scm; extra == "doc"
Requires-Dist: sphinx>=7; extra == "doc"
Requires-Dist: sphinx-autoapi; extra == "doc"
Requires-Dist: sphinx-design; extra == "doc"
Requires-Dist: sphinx-tabs; extra == "doc"
Requires-Dist: sphinx; extra == "doc"
Provides-Extra: all
Requires-Dist: spec2nexus[dev,doc]; extra == "all"
Dynamic: license-file
